learngene/auto_learngene/__init__.py
learngene/auto_learngene/extract_learngene.py
learngene/auto_learngene/initialize_w_learngene.py
learngene/auto_learngene/pretrained_collective.py
learngene/auto_learngene/train_learngene.py
learngene/auto_learngene/utils/__init__.py
learngene/auto_learngene/utils/meta_optimizers.py
learngene/auto_learngene/utils/utils.py
learngene/auto_learngene/utils/conf/__init__.py
learngene/auto_learngene/utils/conf/global_settings.py
learngene/auto_learngene/utils/models/__init__.py
learngene/auto_learngene/utils/models/beit.py
learngene/auto_learngene/utils/models/distiller.py
learngene/auto_learngene/utils/models/load_settings.py
learngene/auto_learngene/utils/models/model_transformer.py
learngene/auto_learngene/utils/models/modules.py
learngene/auto_learngene/utils/models/res12.py
learngene/auto_learngene/utils/models/resnet_cifar.py
learngene/auto_learngene/utils/models/resnet_ilsvrc.py
learngene/auto_learngene/utils/models/resnet_v2.py
learngene/auto_learngene/utils/models/utils.py
learngene/auto_learngene/utils/models/vgg_cifar.py
learngene/auto_learngene/utils/models/vgg_ilsvrc.py
learngene/auto_learngene/utils/models/vision_transformer.py
learngene/auto_learngene/utils/models/vision_transformer_wfeature.py
learngene/auto_learngene/utils/models/vit.py
learngene/auto_learngene/utils/models/vit_google.py
learngene/data_all/__init__.py
learngene/data_all/dataloader/__init__.py
learngene/data_all/dataloader/dataloader.py
learngene/data_all/datasets/__init__.py
learngene/data_all/datasets/auto_makedata.py
learngene/data_all/datasets/heur_makedata.py
learngene/heur_learngene/__init__.py
learngene/heur_learngene/extract_learngene.py
learngene/heur_learngene/initialize_w_learngene.py
learngene/heur_learngene/train_learngene.py
learngene/heur_learngene/utils/Ewc_class.py
learngene/heur_learngene/utils/__init__.py
learngene/heur_learngene/utils/exp_model.py
learngene/heur_learngene/utils/network_wider.py
learngene-1.0.0.dist-info/LICENSE.txt
learngene-1.0.0.dist-info/METADATA
learngene-1.0.0.dist-info/WHEEL
learngene-1.0.0.dist-info/top_level.txt
learngene-1.0.0.dist-info/RECORD
